{
  "project_info": {
    "project_number": "936574859905",
    "project_id": "healthbingo-a3be7",
    "storage_bucket": "healthbingo-a3be7.firebasestorage.app"
  },
  "client": [
    {
      "client_info": {
        "mobilesdk_app_id": "1:936574859905:android:40537f4ff3f41090e1ab80",
        "android_client_info": {
          "package_name": "com.healthbingo"
        }
      },
      "oauth_client": [],
      "api_key": [
        {
          "current_key": "AIzaSyCV-_bTYzbGEjBJKPROnPOox14qpJ0XRFk"
        }
      ],
      "services": {
        "appinvite_service": {
          "other_platform_oauth_client": []
        }
      }
    }
  ],
  "configuration_version": "1"
}